hpkerga/__init__.py
hpkerga/__main__.py
hpkerga/empty_conf.yaml
hpkerga/send_config.py
hpkerga-0.1.4.dist-info/LICENSE
hpkerga-0.1.4.dist-info/METADATA
hpkerga-0.1.4.dist-info/WHEEL
hpkerga-0.1.4.dist-info/top_level.txt
hpkerga-0.1.4.dist-info/RECORD
