Metadata-Version: 2.1
Name: hpkerga
Version: 0.1.4
Summary: hp.kerga.fr
Home-page: UNKNOWN
License: UNKNOWN
Platform: UNKNOWN
Classifier: Programming Language :: Python :: 3
Classifier: License :: OSI Approved :: MIT License
Classifier: Operating System :: OS Independent
License-File: LICENSE
